kidoredis/__init__.py
kidoredis/backends.py
kidoredis/models.py
kidoredis/compat.py
django_kidoredis-1.0.dist-info/top_level.txt
django_kidoredis-1.0.dist-info/METADATA
django_kidoredis-1.0.dist-info/DESCRIPTION.rst
django_kidoredis-1.0.dist-info/metadata.json
django_kidoredis-1.0.dist-info/WHEEL
django_kidoredis-1.0.dist-info/RECORD
