Metadata-Version: 2.0
Name: django-kidoredis
Version: 1.0
Summary: Django redis backend
Home-page: http://kidosoft.pl
Author: Jakub STOLARSKI (Dryobates)
Author-email: jakub.stolarski@kidosoft.pl
License: beerware
Keywords: django redis
Platform: UNKNOWN
Classifier: Development Status :: 4 - Beta
Classifier: Environment :: Web Environment
Classifier: Intended Audience :: Developers
Classifier: License :: OSI Approved :: BSD License
Classifier: Operating System :: OS Independent
Classifier: Framework :: Django
Classifier: Programming Language :: Python
Classifier: Topic :: Software Development :: Libraries :: Python Modules
Requires-Dist: redis
Requires-Dist: hash-ring
